terraria_pc_apis_ids/__init__.py
terraria_pc_apis_ids/terraria_pc_apis_ids.py
terraria_pc_apis_ids-1.0.1.dist-info/LICENSE
terraria_pc_apis_ids-1.0.1.dist-info/METADATA
terraria_pc_apis_ids-1.0.1.dist-info/WHEEL
terraria_pc_apis_ids-1.0.1.dist-info/top_level.txt
terraria_pc_apis_ids-1.0.1.dist-info/RECORD
