Metadata-Version: 2.1
Name: terraria-pc-apis-ids
Version: 1.0.1
Summary: IDs for pc terraria APIs
Home-page: https://gitlab.com/fkwilczek/terraria-pc-apis-ids
Author: Filip K
Author-email: fkwilczek@gmail.com
License: GNU General Public License v3 (GPLv3)
Platform: UNKNOWN
Classifier: Programming Language :: Python :: 3
Classifier: Operating System :: OS Independent
Classifier: License :: OSI Approved :: GNU General Public License v3 (GPLv3)
License-File: LICENSE
